{
  "type": "SecondaryTheme",
  "number": 6233,
  "title": "rejection, human experience of",
  "comment": "Feelings of rejection by God may be a result of alienation caused directly or indirectly by sin. God's people also experience rejection by a hostile world. Experiences and feelings of rejection are to be met with prayer, forgiveness and perseverance, together with confidence in God's commitment to and compassion for, his people.",
  "primaryref": null,
  "children": [
    {
      "type": "CommentSubheading",
      "title": "Feelings of rejection by God",
      "precomment": "",
      "refgroups": [],
      "comment": "",
      "children": [
        {
          "type": "CommentSubheadingTitle",
          "title": "Feelings of national rejection",
          "precomment": "",
          "refgroups": [
            {
              "type": "ReferenceGroup",
              "primaryrefs": [
                {
                  "type": "Reference",
                  "refclass": "A",
                  "comment": "",
                  "continuation": false,
                  "bcvreferences": [
                    "19074001"
                  ],
                  "parallels": []
                },
                {
                  "type": "Reference",
                  "refclass": "A",
                  "comment": "",
                  "continuation": true,
                  "bcvreferences": [
                    "23049014"
                  ],
                  "parallels": []
                }
              ],
              "secondaryrefs": [],
              "seealsos": [
                {
                  "type": "Reference",
                  "refclass": "B",
                  "comment": "",
                  "continuation": false,
                  "bcvreferences": [
                    "19044009",
                    "19108011"
                  ],
                  "parallels": []
                },
                {
                  "type": "Reference",
                  "refclass": "B",
                  "comment": "",
                  "continuation": true,
                  "bcvreferences": [
                    "23040027"
                  ],
                  "parallels": []
                },
                {
                  "type": "Reference",
                  "refclass": "B",
                  "comment": "",
                  "continuation": true,
                  "bcvreferences": [
                    "24013017",
                    "24014009"
                  ],
                  "parallels": []
                },
                {
                  "type": "Reference",
                  "refclass": "B",
                  "comment": "",
                  "continuation": true,
                  "bcvreferences": [
                    "25001002",
                    "25005020"
                  ],
                  "parallels": []
                },
                {
                  "type": "Reference",
                  "refclass": "B",
                  "comment": "",
                  "continuation": true,
                  "bcvreferences": [
                    "26037011"
                  ],
                  "parallels": []
                }
              ]
            }
          ]
        },
        {
          "type": "CommentSubheadingTitle",
          "title": "Feelings of personal rejection",
          "precomment": "",
          "refgroups": [
            {
              "type": "ReferenceGroup",
              "primaryrefs": [
                {
                  "type": "Reference",
                  "refclass": "A",
                  "comment": "",
                  "continuation": false,
                  "bcvreferences": [
                    "19013001"
                  ],
                  "parallels": []
                },
                {
                  "type": "Reference",
                  "refclass": "A",
                  "comment": "Jesus Christ experiences separation from his Father as a consequence of bearing human sin.",
                  "continuation": true,
                  "bcvreferences": [
                    "40027046"
                  ],
                  "parallels": [
                    "41015034"
                  ]
                }
              ],
              "secondaryrefs": [],
              "seealsos": [
                {
                  "type": "Reference",
                  "refclass": "B",
                  "comment": "",
                  "continuation": false,
                  "bcvreferences": [
                    "19022001-19022002",
                    "19043002",
                    "19088014"
                  ],
                  "parallels": []
                }
              ]
            }
          ]
        }
      ]
    },
    {
      "type": "CommentSubheading",
      "title": "God's servants experience rejection",
      "precomment": "",
      "refgroups": [],
      "comment": "",
      "children": [
        {
          "type": "CommentSubheadingTitle",
          "title": "Samuel",
          "precomment": "",
          "refgroups": [
            {
              "type": "ReferenceGroup",
              "primaryrefs": [
                {
                  "type": "Reference",
                  "refclass": "A",
                  "comment": "",
                  "continuation": false,
                  "bcvreferences": [
                    "09008005-09008007"
                  ],
                  "parallels": []
                }
              ],
              "secondaryrefs": [],
              "seealsos": []
            }
          ]
        },
        {
          "type": "CommentSubheadingTitle",
          "title": "Elijah",
          "precomment": "",
          "refgroups": [
            {
              "type": "ReferenceGroup",
              "primaryrefs": [
                {
                  "type": "Reference",
                  "refclass": "A",
                  "comment": "",
                  "continuation": false,
                  "bcvreferences": [
                    "11019010"
                  ],
                  "parallels": []
                }
              ],
              "secondaryrefs": [],
              "seealsos": [
                {
                  "type": "Reference",
                  "refclass": "B",
                  "comment": "",
                  "continuation": false,
                  "bcvreferences": [
                    "11018022",
                    "11019001-11019004"
                  ],
                  "parallels": []
                }
              ]
            }
          ]
        },
        {
          "type": "CommentSubheadingTitle",
          "title": "The psalmist",
          "precomment": "",
          "refgroups": [
            {
              "type": "ReferenceGroup",
              "primaryrefs": [
                {
                  "type": "Reference",
                  "refclass": "A",
                  "comment": "",
                  "continuation": false,
                  "bcvreferences": [
                    "19041007"
                  ],
                  "parallels": []
                }
              ],
              "secondaryrefs": [],
              "seealsos": [
                {
                  "type": "Reference",
                  "refclass": "B",
                  "comment": "",
                  "continuation": false,
                  "bcvreferences": [
                    "19022006-19022008",
                    "19031012-19031013",
                    "19069020",
                    "19071010"
                  ],
                  "parallels": []
                }
              ]
            }
          ]
        },
        {
          "type": "CommentSubheadingTitle",
          "title": "Jeremiah",
          "precomment": "",
          "refgroups": [
            {
              "type": "ReferenceGroup",
              "primaryrefs": [
                {
                  "type": "Reference",
                  "refclass": "A",
                  "comment": "",
                  "continuation": false,
                  "bcvreferences": [
                    "24015010"
                  ],
                  "parallels": []
                }
              ],
              "secondaryrefs": [],
              "seealsos": [
                {
                  "type": "Reference",
                  "refclass": "B",
                  "comment": "",
                  "continuation": false,
                  "bcvreferences": [
                    "24020007-24020009",
                    "24020014-24020015",
                    "24020018"
                  ],
                  "parallels": []
                }
              ]
            }
          ]
        },
        {
          "type": "CommentSubheadingTitle",
          "title": "Jesus Christ",
          "precomment": "",
          "refgroups": [
            {
              "type": "ReferenceGroup",
              "primaryrefs": [
                {
                  "type": "Reference",
                  "refclass": "A",
                  "comment": "",
                  "continuation": false,
                  "bcvreferences": [
                    "23053005"
                  ],
                  "parallels": []
                },
                {
                  "type": "Reference",
                  "refclass": "A",
                  "comment": "",
                  "continuation": true,
                  "bcvreferences": [
                    "43001011"
                  ],
                  "parallels": []
                }
              ],
              "secondaryrefs": [],
              "seealsos": [
                {
                  "type": "Reference",
                  "refclass": "B",
                  "comment": "",
                  "continuation": false,
                  "bcvreferences": [
                    "42023018"
                  ],
                  "parallels": []
                }
              ]
            }
          ]
        },
        {
          "type": "CommentSubheadingTitle",
          "title": "Jesus Christ's disciples",
          "precomment": "",
          "refgroups": [
            {
              "type": "ReferenceGroup",
              "primaryrefs": [
                {
                  "type": "Reference",
                  "refclass": "A",
                  "comment": "",
                  "continuation": false,
                  "bcvreferences": [
                    "43015018"
                  ],
                  "parallels": []
                }
              ],
              "secondaryrefs": [],
              "seealsos": [
                {
                  "type": "Reference",
                  "refclass": "B",
                  "comment": "",
                  "continuation": false,
                  "bcvreferences": [
                    "40005010-40005011"
                  ],
                  "parallels": [
                    "42006022"
                  ]
                },
                {
                  "type": "Reference",
                  "refclass": "B",
                  "comment": "",
                  "continuation": true,
                  "bcvreferences": [
                    "43017014"
                  ],
                  "parallels": []
                },
                {
                  "type": "Reference",
                  "refclass": "B",
                  "comment": "",
                  "continuation": true,
                  "bcvreferences": [
                    "44013050",
                    "44014019",
                    "44016022"
                  ],
                  "parallels": []
                },
                {
                  "type": "Reference",
                  "refclass": "B",
                  "comment": "",
                  "continuation": true,
                  "bcvreferences": [
                    "55003012"
                  ],
                  "parallels": []
                },
                {
                  "type": "Reference",
                  "refclass": "B",
                  "comment": "",
                  "continuation": true,
                  "bcvreferences": [
                    "60004012"
                  ],
                  "parallels": []
                }
              ]
            }
          ]
        }
      ]
    },
    {
      "type": "CommentSubheading",
      "title": "Responding to rejection",
      "precomment": "",
      "refgroups": [],
      "comment": "",
      "children": [
        {
          "type": "CommentSubheadingTitle",
          "title": "Appealing to God",
          "precomment": "",
          "refgroups": [
            {
              "type": "ReferenceGroup",
              "primaryrefs": [
                {
                  "type": "Reference",
                  "refclass": "A",
                  "comment": "",
                  "continuation": false,
                  "bcvreferences": [
                    "14006042"
                  ],
                  "parallels": []
                },
                {
                  "type": "Reference",
                  "refclass": "A",
                  "comment": "",
                  "continuation": true,
                  "bcvreferences": [
                    "19027009",
                    "19071012"
                  ],
                  "parallels": []
                }
              ],
              "secondaryrefs": [],
              "seealsos": [
                {
                  "type": "Reference",
                  "refclass": "B",
                  "comment": "",
                  "continuation": false,
                  "bcvreferences": [
                    "19022009-19022011",
                    "19022019-19022021",
                    "19044023-19044024",
                    "19051011-19051012",
                    "19077007-19077012",
                    "19132010"
                  ],
                  "parallels": []
                },
                {
                  "type": "Reference",
                  "refclass": "B",
                  "comment": "",
                  "continuation": true,
                  "bcvreferences": [
                    "24015015",
                    "24020012"
                  ],
                  "parallels": []
                },
                {
                  "type": "Reference",
                  "refclass": "B",
                  "comment": "",
                  "continuation": true,
                  "bcvreferences": [
                    "25005021-25005022"
                  ],
                  "parallels": []
                }
              ]
            }
          ]
        },
        {
          "type": "CommentSubheadingTitle",
          "title": "Offering forgiveness",
          "precomment": "",
          "refgroups": [
            {
              "type": "ReferenceGroup",
              "primaryrefs": [
                {
                  "type": "Reference",
                  "refclass": "A",
                  "comment": "",
                  "continuation": false,
                  "bcvreferences": [
                    "42023034"
                  ],
                  "parallels": []
                }
              ],
              "secondaryrefs": [],
              "seealsos": [
                {
                  "type": "Reference",
                  "refclass": "B",
                  "comment": "",
                  "continuation": false,
                  "bcvreferences": [
                    "01050017"
                  ],
                  "parallels": []
                },
                {
                  "type": "Reference",
                  "refclass": "B",
                  "comment": "",
                  "continuation": true,
                  "bcvreferences": [
                    "44007059-44007060"
                  ],
                  "parallels": []
                },
                {
                  "type": "Reference",
                  "refclass": "B",
                  "comment": "",
                  "continuation": true,
                  "bcvreferences": [
                    "55004016"
                  ],
                  "parallels": []
                }
              ]
            }
          ]
        },
        {
          "type": "CommentSubheadingTitle",
          "title": "Rejoicing in suffering",
          "precomment": "",
          "refgroups": [
            {
              "type": "ReferenceGroup",
              "primaryrefs": [],
              "secondaryrefs": [
                {
                  "type": "Reference",
                  "refclass": "B",
                  "comment": "",
                  "continuation": false,
                  "bcvreferences": [
                    "40005011-40005012"
                  ],
                  "parallels": [
                    "42006022-42006023"
                  ]
                },
                {
                  "type": "Reference",
                  "refclass": "B",
                  "comment": "",
                  "continuation": true,
                  "bcvreferences": [
                    "44005041"
                  ],
                  "parallels": []
                },
                {
                  "type": "Reference",
                  "refclass": "B",
                  "comment": "",
                  "continuation": true,
                  "bcvreferences": [
                    "45005003"
                  ],
                  "parallels": []
                },
                {
                  "type": "Reference",
                  "refclass": "B",
                  "comment": "",
                  "continuation": true,
                  "bcvreferences": [
                    "59001002-59001003"
                  ],
                  "parallels": []
                }
              ],
              "seealsos": []
            }
          ]
        },
        {
          "type": "CommentSubheadingTitle",
          "title": "Persevering",
          "precomment": "",
          "refgroups": [
            {
              "type": "ReferenceGroup",
              "primaryrefs": [],
              "secondaryrefs": [
                {
                  "type": "Reference",
                  "refclass": "B",
                  "comment": "",
                  "continuation": false,
                  "bcvreferences": [
                    "44005028-44005029",
                    "44005042"
                  ],
                  "parallels": []
                }
              ],
              "seealsos": []
            }
          ]
        }
      ]
    },
    {
      "type": "CommentSubheading",
      "title": "Encouragement for those experiencing rejection",
      "precomment": "",
      "refgroups": [],
      "comment": "",
      "children": [
        {
          "type": "CommentSubheadingTitle",
          "title": "God's commitment to his people",
          "precomment": "",
          "refgroups": [
            {
              "type": "ReferenceGroup",
              "primaryrefs": [
                {
                  "type": "Reference",
                  "refclass": "A",
                  "comment": "",
                  "continuation": false,
                  "bcvreferences": [
                    "23049015-23049016"
                  ],
                  "parallels": []
                }
              ],
              "secondaryrefs": [],
              "seealsos": [
                {
                  "type": "Reference",
                  "refclass": "B",
                  "comment": "",
                  "continuation": false,
                  "bcvreferences": [
                    "19027010",
                    "19094014"
                  ],
                  "parallels": []
                },
                {
                  "type": "Reference",
                  "refclass": "B",
                  "comment": "",
                  "continuation": true,
                  "bcvreferences": [
                    "24031020"
                  ],
                  "parallels": []
                },
                {
                  "type": "Reference",
                  "refclass": "B",
                  "comment": "",
                  "continuation": true,
                  "bcvreferences": [
                    "25003021-25003024"
                  ],
                  "parallels": []
                },
                {
                  "type": "Reference",
                  "refclass": "B",
                  "comment": "",
                  "continuation": true,
                  "bcvreferences": [
                    "28011001-28011004"
                  ],
                  "parallels": []
                },
                {
                  "type": "Reference",
                  "refclass": "B",
                  "comment": "",
                  "continuation": true,
                  "bcvreferences": [
                    "40010030-40010031"
                  ],
                  "parallels": [
                    "42012007"
                  ]
                }
              ]
            }
          ]
        },
        {
          "type": "CommentSubheadingTitle",
          "title": "God's compassion and forgiveness",
          "precomment": "",
          "refgroups": [
            {
              "type": "ReferenceGroup",
              "primaryrefs": [
                {
                  "type": "Reference",
                  "refclass": "A",
                  "comment": "",
                  "continuation": false,
                  "bcvreferences": [
                    "25003031-25003032"
                  ],
                  "parallels": []
                }
              ],
              "secondaryrefs": [],
              "seealsos": [
                {
                  "type": "Reference",
                  "refclass": "B",
                  "comment": "",
                  "continuation": false,
                  "bcvreferences": [
                    "05032036"
                  ],
                  "parallels": []
                },
                {
                  "type": "Reference",
                  "refclass": "B",
                  "comment": "",
                  "continuation": true,
                  "bcvreferences": [
                    "19130007-19130008"
                  ],
                  "parallels": []
                },
                {
                  "type": "Reference",
                  "refclass": "B",
                  "comment": "",
                  "continuation": true,
                  "bcvreferences": [
                    "23012001-23012002",
                    "23049013"
                  ],
                  "parallels": []
                },
                {
                  "type": "Reference",
                  "refclass": "B",
                  "comment": "",
                  "continuation": true,
                  "bcvreferences": [
                    "26039025"
                  ],
                  "parallels": []
                },
                {
                  "type": "Reference",
                  "refclass": "B",
                  "comment": "",
                  "continuation": true,
                  "bcvreferences": [
                    "28011008-28011009"
                  ],
                  "parallels": []
                },
                {
                  "type": "Reference",
                  "refclass": "B",
                  "comment": "God's readiness to forgive is to be reflected in the attitude of his people towards one another.",
                  "continuation": true,
                  "bcvreferences": [
                    "47002007-47002008"
                  ],
                  "parallels": []
                }
              ]
            }
          ]
        },
        {
          "type": "CommentSubheadingTitle",
          "title": "God's strengthening",
          "precomment": "",
          "refgroups": [
            {
              "type": "ReferenceGroup",
              "primaryrefs": [],
              "secondaryrefs": [
                {
                  "type": "Reference",
                  "refclass": "B",
                  "comment": "",
                  "continuation": false,
                  "bcvreferences": [
                    "23040028-23040031"
                  ],
                  "parallels": []
                },
                {
                  "type": "Reference",
                  "refclass": "B",
                  "comment": "",
                  "continuation": true,
                  "bcvreferences": [
                    "55004017"
                  ],
                  "parallels": []
                }
              ],
              "seealsos": []
            }
          ]
        },
        {
          "type": "CommentSubheadingTitle",
          "title": "God's vindication of his people",
          "precomment": "",
          "refgroups": [
            {
              "type": "ReferenceGroup",
              "primaryrefs": [],
              "secondaryrefs": [
                {
                  "type": "Reference",
                  "refclass": "B",
                  "comment": "",
                  "continuation": false,
                  "bcvreferences": [
                    "19135014"
                  ],
                  "parallels": []
                },
                {
                  "type": "Reference",
                  "refclass": "B",
                  "comment": "",
                  "continuation": true,
                  "bcvreferences": [
                    "23050006-23050009",
                    "23054017"
                  ],
                  "parallels": []
                },
                {
                  "type": "Reference",
                  "refclass": "B",
                  "comment": "",
                  "continuation": true,
                  "bcvreferences": [
                    "45008018"
                  ],
                  "parallels": []
                },
                {
                  "type": "Reference",
                  "refclass": "B",
                  "comment": "",
                  "continuation": true,
                  "bcvreferences": [
                    "60004013"
                  ],
                  "parallels": []
                },
                {
                  "type": "Reference",
                  "refclass": "B",
                  "comment": "",
                  "continuation": true,
                  "bcvreferences": [
                    "66002010"
                  ],
                  "parallels": []
                }
              ],
              "seealsos": []
            }
          ]
        },
        {
          "type": "CommentSubheadingTitle",
          "title": "Support from fellow believers",
          "precomment": "",
          "refgroups": [
            {
              "type": "ReferenceGroup",
              "primaryrefs": [
                {
                  "type": "Reference",
                  "refclass": "A",
                  "comment": "",
                  "continuation": false,
                  "bcvreferences": [
                    "47001004"
                  ],
                  "parallels": []
                }
              ],
              "secondaryrefs": [],
              "seealsos": [
                {
                  "type": "Reference",
                  "refclass": "B",
                  "comment": "",
                  "continuation": false,
                  "bcvreferences": [
                    "44014022"
                  ],
                  "parallels": []
                },
                {
                  "type": "Reference",
                  "refclass": "B",
                  "comment": "",
                  "continuation": true,
                  "bcvreferences": [
                    "47006006-47006007"
                  ],
                  "parallels": []
                }
              ]
            }
          ]
        }
      ]
    }
  ],
  "see": [],
  "seealsos": [
    1030,
    1085,
    1320,
    5770,
    5789,
    5799,
    5820,
    5927,
    6115,
    6652,
    8602,
    8794
  ]
}