{
  "type": "SecondaryTheme",
  "number": 8326,
  "title": "purity, moral and spiritual",
  "comment": "Moral and spiritual purity is demanded by God of his people. God calls his people to be holy, just as he is holy.",
  "primaryref": null,
  "children": [
    {
      "type": "CommentSubheading",
      "title": "Divine purity",
      "precomment": "",
      "refgroups": [],
      "comment": "",
      "children": [
        {
          "type": "CommentSubheadingTitle",
          "title": "The purity of God",
          "precomment": "",
          "refgroups": [
            {
              "type": "ReferenceGroup",
              "primaryrefs": [
                {
                  "type": "Reference",
                  "refclass": "A",
                  "comment": "",
                  "continuation": false,
                  "bcvreferences": [
                    "35001013"
                  ],
                  "parallels": []
                }
              ],
              "secondaryrefs": [],
              "seealsos": [
                {
                  "type": "Reference",
                  "refclass": "B",
                  "comment": "",
                  "continuation": false,
                  "bcvreferences": [
                    "18004017"
                  ],
                  "parallels": []
                },
                {
                  "type": "Reference",
                  "refclass": "B",
                  "comment": "",
                  "continuation": true,
                  "bcvreferences": [
                    "19018026"
                  ],
                  "parallels": []
                },
                {
                  "type": "Reference",
                  "refclass": "B",
                  "comment": "",
                  "continuation": true,
                  "bcvreferences": [
                    "62001005"
                  ],
                  "parallels": []
                }
              ]
            }
          ]
        },
        {
          "type": "CommentSubheadingTitle",
          "title": "The purity of Jesus Christ",
          "precomment": "",
          "refgroups": [
            {
              "type": "ReferenceGroup",
              "primaryrefs": [
                {
                  "type": "Reference",
                  "refclass": "A",
                  "comment": "",
                  "continuation": false,
                  "bcvreferences": [
                    "62003003"
                  ],
                  "parallels": []
                }
              ],
              "secondaryrefs": [],
              "seealsos": [
                {
                  "type": "Reference",
                  "refclass": "B",
                  "comment": "",
                  "continuation": false,
                  "bcvreferences": [
                    "40017002"
                  ],
                  "parallels": []
                },
                {
                  "type": "Reference",
                  "refclass": "B",
                  "comment": "",
                  "continuation": true,
                  "bcvreferences": [
                    "58007026"
                  ],
                  "parallels": []
                }
              ]
            }
          ]
        }
      ]
    },
    {
      "type": "CommentSubheading",
      "title": "Fellowship with God demands purity",
      "precomment": "",
      "refgroups": [
        {
          "type": "ReferenceGroup",
          "primaryrefs": [
            {
              "type": "Reference",
              "refclass": "A",
              "comment": "",
              "continuation": false,
              "bcvreferences": [
                "19024003-19024004"
              ],
              "parallels": []
            },
            {
              "type": "Reference",
              "refclass": "A",
              "comment": "",
              "continuation": true,
              "bcvreferences": [
                "40005008"
              ],
              "parallels": []
            }
          ],
          "secondaryrefs": [],
          "seealsos": [
            {
              "type": "Reference",
              "refclass": "B",
              "comment": "",
              "continuation": false,
              "bcvreferences": [
                "19051006",
                "19073001"
              ],
              "parallels": []
            }
          ]
        }
      ],
      "comment": "",
      "children": []
    },
    {
      "type": "CommentSubheading",
      "title": "God's people are to live pure lives",
      "precomment": "",
      "refgroups": [
        {
          "type": "ReferenceGroup",
          "primaryrefs": [
            {
              "type": "Reference",
              "refclass": "A",
              "comment": "",
              "continuation": false,
              "bcvreferences": [
                "51003005"
              ],
              "parallels": []
            }
          ],
          "secondaryrefs": [],
          "seealsos": [
            {
              "type": "Reference",
              "refclass": "B",
              "comment": "",
              "continuation": false,
              "bcvreferences": [
                "03018030"
              ],
              "parallels": []
            },
            {
              "type": "Reference",
              "refclass": "B",
              "comment": "",
              "continuation": true,
              "bcvreferences": [
                "18031001"
              ],
              "parallels": []
            },
            {
              "type": "Reference",
              "refclass": "B",
              "comment": "",
              "continuation": true,
              "bcvreferences": [
                "19051010"
              ],
              "parallels": []
            },
            {
              "type": "Reference",
              "refclass": "B",
              "comment": "Yeast is a symbol of sin",
              "continuation": true,
              "bcvreferences": [
                "46005007-46005008"
              ],
              "parallels": []
            },
            {
              "type": "Reference",
              "refclass": "B",
              "comment": "",
              "continuation": true,
              "bcvreferences": [
                "46006015-46006020"
              ],
              "parallels": []
            },
            {
              "type": "Reference",
              "refclass": "B",
              "comment": "",
              "continuation": true,
              "bcvreferences": [
                "52004003"
              ],
              "parallels": []
            },
            {
              "type": "Reference",
              "refclass": "B",
              "comment": "",
              "continuation": true,
              "bcvreferences": [
                "56001015",
                "56002005"
              ],
              "parallels": []
            },
            {
              "type": "Reference",
              "refclass": "B",
              "comment": "",
              "continuation": true,
              "bcvreferences": [
                "58013004"
              ],
              "parallels": []
            },
            {
              "type": "Reference",
              "refclass": "B",
              "comment": "",
              "continuation": true,
              "bcvreferences": [
                "59001027",
                "59004008"
              ],
              "parallels": []
            }
          ]
        }
      ],
      "comment": "",
      "children": []
    },
    {
      "type": "CommentSubheading",
      "title": "Purity is unobtainable by human effort",
      "precomment": "",
      "refgroups": [],
      "comment": "",
      "children": [
        {
          "type": "CommentSubheadingTitle",
          "title": "Because of the sinful human nature",
          "precomment": "",
          "refgroups": [
            {
              "type": "ReferenceGroup",
              "primaryrefs": [
                {
                  "type": "Reference",
                  "refclass": "A",
                  "comment": "",
                  "continuation": false,
                  "bcvreferences": [
                    "18014004"
                  ],
                  "parallels": []
                }
              ],
              "secondaryrefs": [],
              "seealsos": [
                {
                  "type": "Reference",
                  "refclass": "B",
                  "comment": "",
                  "continuation": false,
                  "bcvreferences": [
                    "18015014",
                    "18025004"
                  ],
                  "parallels": []
                },
                {
                  "type": "Reference",
                  "refclass": "B",
                  "comment": "",
                  "continuation": true,
                  "bcvreferences": [
                    "21007020"
                  ],
                  "parallels": []
                }
              ]
            }
          ]
        },
        {
          "type": "CommentSubheadingTitle",
          "title": "Because of the tendency to idolatry",
          "precomment": "",
          "refgroups": [
            {
              "type": "ReferenceGroup",
              "primaryrefs": [
                {
                  "type": "Reference",
                  "refclass": "A",
                  "comment": "",
                  "continuation": false,
                  "bcvreferences": [
                    "28008005"
                  ],
                  "parallels": []
                }
              ],
              "secondaryrefs": [],
              "seealsos": []
            }
          ]
        },
        {
          "type": "CommentSubheadingTitle",
          "title": "Because of self-deception",
          "precomment": "",
          "refgroups": [
            {
              "type": "ReferenceGroup",
              "primaryrefs": [
                {
                  "type": "Reference",
                  "refclass": "A",
                  "comment": "",
                  "continuation": false,
                  "bcvreferences": [
                    "20030012"
                  ],
                  "parallels": []
                }
              ],
              "secondaryrefs": [],
              "seealsos": [
                {
                  "type": "Reference",
                  "refclass": "B",
                  "comment": "",
                  "continuation": false,
                  "bcvreferences": [
                    "20020009"
                  ],
                  "parallels": []
                }
              ]
            }
          ]
        },
        {
          "type": "CommentSubheadingTitle",
          "title": "Because of an unwillingness to be cleansed",
          "precomment": "",
          "refgroups": [
            {
              "type": "ReferenceGroup",
              "primaryrefs": [
                {
                  "type": "Reference",
                  "refclass": "A",
                  "comment": "",
                  "continuation": false,
                  "bcvreferences": [
                    "26024013"
                  ],
                  "parallels": []
                }
              ],
              "secondaryrefs": [],
              "seealsos": []
            }
          ]
        }
      ]
    },
    {
      "type": "CommentSubheading",
      "title": "Symbols of purification from sin",
      "precomment": "",
      "refgroups": [
        {
          "type": "ReferenceGroup",
          "primaryrefs": [
            {
              "type": "Reference",
              "refclass": "A",
              "comment": "",
              "continuation": false,
              "bcvreferences": [
                "19051007"
              ],
              "parallels": []
            }
          ],
          "secondaryrefs": [],
          "seealsos": [
            {
              "type": "Reference",
              "refclass": "B",
              "comment": "fire",
              "continuation": false,
              "bcvreferences": [
                "23006006"
              ],
              "parallels": []
            },
            {
              "type": "Reference",
              "refclass": "B",
              "comment": "water baptism",
              "continuation": true,
              "bcvreferences": [
                "41001004"
              ],
              "parallels": []
            },
            {
              "type": "Reference",
              "refclass": "B",
              "comment": "virginity",
              "continuation": true,
              "bcvreferences": [
                "47011002"
              ],
              "parallels": []
            },
            {
              "type": "Reference",
              "refclass": "B",
              "comment": "spotlessness",
              "continuation": true,
              "bcvreferences": [
                "61003014"
              ],
              "parallels": []
            }
          ]
        }
      ],
      "comment": "",
      "children": []
    },
    {
      "type": "CommentSubheading",
      "title": "God promises to purify his people",
      "precomment": "",
      "refgroups": [
        {
          "type": "ReferenceGroup",
          "primaryrefs": [
            {
              "type": "Reference",
              "refclass": "A",
              "comment": "",
              "continuation": false,
              "bcvreferences": [
                "26036025"
              ],
              "parallels": []
            }
          ],
          "secondaryrefs": [],
          "seealsos": [
            {
              "type": "Reference",
              "refclass": "B",
              "comment": "",
              "continuation": false,
              "bcvreferences": [
                "36003009"
              ],
              "parallels": []
            },
            {
              "type": "Reference",
              "refclass": "B",
              "comment": "",
              "continuation": true,
              "bcvreferences": [
                "38013001"
              ],
              "parallels": []
            }
          ]
        }
      ],
      "comment": "",
      "children": []
    },
    {
      "type": "CommentSubheading",
      "title": "Purification through Jesus Christ",
      "precomment": "",
      "refgroups": [],
      "comment": "",
      "children": [
        {
          "type": "CommentSubheadingTitle",
          "title": "Through pardon offered in his death",
          "precomment": "",
          "refgroups": [
            {
              "type": "ReferenceGroup",
              "primaryrefs": [
                {
                  "type": "Reference",
                  "refclass": "A",
                  "comment": "",
                  "continuation": false,
                  "bcvreferences": [
                    "58009014"
                  ],
                  "parallels": []
                }
              ],
              "secondaryrefs": [],
              "seealsos": [
                {
                  "type": "Reference",
                  "refclass": "B",
                  "comment": "",
                  "continuation": false,
                  "bcvreferences": [
                    "58012024"
                  ],
                  "parallels": []
                },
                {
                  "type": "Reference",
                  "refclass": "B",
                  "comment": "",
                  "continuation": true,
                  "bcvreferences": [
                    "62001007"
                  ],
                  "parallels": []
                }
              ]
            }
          ]
        },
        {
          "type": "CommentSubheadingTitle",
          "title": "Through his word",
          "precomment": "",
          "refgroups": [
            {
              "type": "ReferenceGroup",
              "primaryrefs": [
                {
                  "type": "Reference",
                  "refclass": "A",
                  "comment": "",
                  "continuation": false,
                  "bcvreferences": [
                    "43015003"
                  ],
                  "parallels": []
                }
              ],
              "secondaryrefs": [],
              "seealsos": [
                {
                  "type": "Reference",
                  "refclass": "B",
                  "comment": "",
                  "continuation": false,
                  "bcvreferences": [
                    "43013010"
                  ],
                  "parallels": []
                }
              ]
            }
          ]
        },
        {
          "type": "CommentSubheadingTitle",
          "title": "Through his presence in resisting temptation",
          "precomment": "",
          "refgroups": [
            {
              "type": "ReferenceGroup",
              "primaryrefs": [
                {
                  "type": "Reference",
                  "refclass": "A",
                  "comment": "",
                  "continuation": false,
                  "bcvreferences": [
                    "59004007-59004008"
                  ],
                  "parallels": []
                }
              ],
              "secondaryrefs": [],
              "seealsos": [
                {
                  "type": "Reference",
                  "refclass": "B",
                  "comment": "",
                  "continuation": false,
                  "bcvreferences": [
                    "60005009"
                  ],
                  "parallels": []
                }
              ]
            }
          ]
        },
        {
          "type": "CommentSubheadingTitle",
          "title": "Through hope built on his promises",
          "precomment": "",
          "refgroups": [
            {
              "type": "ReferenceGroup",
              "primaryrefs": [
                {
                  "type": "Reference",
                  "refclass": "A",
                  "comment": "",
                  "continuation": false,
                  "bcvreferences": [
                    "56002012-56002013"
                  ],
                  "parallels": []
                }
              ],
              "secondaryrefs": [],
              "seealsos": [
                {
                  "type": "Reference",
                  "refclass": "B",
                  "comment": "",
                  "continuation": false,
                  "bcvreferences": [
                    "62003003"
                  ],
                  "parallels": []
                }
              ]
            }
          ]
        }
      ]
    },
    {
      "type": "CommentSubheading",
      "title": "Purification through judgment",
      "precomment": "",
      "refgroups": [],
      "comment": "",
      "children": [
        {
          "type": "CommentSubheadingTitle",
          "title": "In the OT",
          "precomment": "",
          "refgroups": [
            {
              "type": "ReferenceGroup",
              "primaryrefs": [
                {
                  "type": "Reference",
                  "refclass": "A",
                  "comment": "",
                  "continuation": false,
                  "bcvreferences": [
                    "03018028"
                  ],
                  "parallels": []
                }
              ],
              "secondaryrefs": [],
              "seealsos": [
                {
                  "type": "Reference",
                  "refclass": "B",
                  "comment": "",
                  "continuation": false,
                  "bcvreferences": [
                    "05013005",
                    "05017007",
                    "05017012"
                  ],
                  "parallels": []
                },
                {
                  "type": "Reference",
                  "refclass": "B",
                  "comment": "",
                  "continuation": true,
                  "bcvreferences": [
                    "07020013"
                  ],
                  "parallels": []
                },
                {
                  "type": "Reference",
                  "refclass": "B",
                  "comment": "",
                  "continuation": true,
                  "bcvreferences": [
                    "39003002-39003004"
                  ],
                  "parallels": []
                }
              ]
            }
          ]
        },
        {
          "type": "CommentSubheadingTitle",
          "title": "In the NT",
          "precomment": "",
          "refgroups": [
            {
              "type": "ReferenceGroup",
              "primaryrefs": [
                {
                  "type": "Reference",
                  "refclass": "A",
                  "comment": "",
                  "continuation": false,
                  "bcvreferences": [
                    "46005013"
                  ],
                  "parallels": []
                }
              ],
              "secondaryrefs": [],
              "seealsos": []
            }
          ]
        }
      ]
    },
    {
      "type": "CommentSubheading",
      "title": "Symbols of purity",
      "precomment": "",
      "refgroups": [],
      "comment": "",
      "children": [
        {
          "type": "CommentSubheadingTitle",
          "title": "Whiteness",
          "precomment": "",
          "refgroups": [
            {
              "type": "ReferenceGroup",
              "primaryrefs": [
                {
                  "type": "Reference",
                  "refclass": "A",
                  "comment": "",
                  "continuation": false,
                  "bcvreferences": [
                    "27007009"
                  ],
                  "parallels": []
                }
              ],
              "secondaryrefs": [],
              "seealsos": [
                {
                  "type": "Reference",
                  "refclass": "B",
                  "comment": "",
                  "continuation": false,
                  "bcvreferences": [
                    "19051007"
                  ],
                  "parallels": []
                },
                {
                  "type": "Reference",
                  "refclass": "B",
                  "comment": "",
                  "continuation": true,
                  "bcvreferences": [
                    "23001018"
                  ],
                  "parallels": []
                },
                {
                  "type": "Reference",
                  "refclass": "B",
                  "comment": "",
                  "continuation": true,
                  "bcvreferences": [
                    "40017002"
                  ],
                  "parallels": [
                    "41009003"
                  ]
                },
                {
                  "type": "Reference",
                  "refclass": "B",
                  "comment": "",
                  "continuation": true,
                  "bcvreferences": [
                    "40028003"
                  ],
                  "parallels": []
                },
                {
                  "type": "Reference",
                  "refclass": "B",
                  "comment": "",
                  "continuation": true,
                  "bcvreferences": [
                    "41016005"
                  ],
                  "parallels": []
                },
                {
                  "type": "Reference",
                  "refclass": "B",
                  "comment": "",
                  "continuation": true,
                  "bcvreferences": [
                    "43020012"
                  ],
                  "parallels": []
                },
                {
                  "type": "Reference",
                  "refclass": "B",
                  "comment": "",
                  "continuation": true,
                  "bcvreferences": [
                    "66001014"
                  ],
                  "parallels": []
                }
              ]
            }
          ]
        },
        {
          "type": "CommentSubheadingTitle",
          "title": "Light",
          "precomment": "",
          "refgroups": [
            {
              "type": "ReferenceGroup",
              "primaryrefs": [
                {
                  "type": "Reference",
                  "refclass": "A",
                  "comment": "",
                  "continuation": false,
                  "bcvreferences": [
                    "62001007"
                  ],
                  "parallels": []
                }
              ],
              "secondaryrefs": [],
              "seealsos": [
                {
                  "type": "Reference",
                  "refclass": "B",
                  "comment": "",
                  "continuation": false,
                  "bcvreferences": [
                    "18025005"
                  ],
                  "parallels": []
                },
                {
                  "type": "Reference",
                  "refclass": "B",
                  "comment": "",
                  "continuation": true,
                  "bcvreferences": [
                    "26001027"
                  ],
                  "parallels": []
                },
                {
                  "type": "Reference",
                  "refclass": "B",
                  "comment": "",
                  "continuation": true,
                  "bcvreferences": [
                    "47006014"
                  ],
                  "parallels": []
                },
                {
                  "type": "Reference",
                  "refclass": "B",
                  "comment": "",
                  "continuation": true,
                  "bcvreferences": [
                    "49005008-49005009"
                  ],
                  "parallels": []
                }
              ]
            }
          ]
        },
        {
          "type": "CommentSubheadingTitle",
          "title": "Washing",
          "precomment": "",
          "refgroups": [
            {
              "type": "ReferenceGroup",
              "primaryrefs": [
                {
                  "type": "Reference",
                  "refclass": "A",
                  "comment": "",
                  "continuation": false,
                  "bcvreferences": [
                    "19026006"
                  ],
                  "parallels": []
                }
              ],
              "secondaryrefs": [],
              "seealsos": [
                {
                  "type": "Reference",
                  "refclass": "B",
                  "comment": "",
                  "continuation": false,
                  "bcvreferences": [
                    "19051002"
                  ],
                  "parallels": []
                }
              ]
            }
          ]
        },
        {
          "type": "CommentSubheadingTitle",
          "title": "Fire",
          "precomment": "",
          "refgroups": [
            {
              "type": "ReferenceGroup",
              "primaryrefs": [
                {
                  "type": "Reference",
                  "refclass": "A",
                  "comment": "",
                  "continuation": false,
                  "bcvreferences": [
                    "27007009-27007010"
                  ],
                  "parallels": []
                }
              ],
              "secondaryrefs": [],
              "seealsos": [
                {
                  "type": "Reference",
                  "refclass": "B",
                  "comment": "",
                  "continuation": false,
                  "bcvreferences": [
                    "23033014"
                  ],
                  "parallels": []
                },
                {
                  "type": "Reference",
                  "refclass": "B",
                  "comment": "",
                  "continuation": true,
                  "bcvreferences": [
                    "26008002"
                  ],
                  "parallels": []
                },
                {
                  "type": "Reference",
                  "refclass": "B",
                  "comment": "",
                  "continuation": true,
                  "bcvreferences": [
                    "66001014-66001015"
                  ],
                  "parallels": []
                }
              ]
            }
          ]
        }
      ]
    }
  ],
  "see": [],
  "seealsos": [
    2054,
    2063,
    4293,
    4826,
    4833,
    5740,
    6187,
    6744,
    8145,
    8266,
    8277
  ]
}